TeLLMgramBot/TeLLMgramBot.py
TeLLMgramBot/__init__.py
TeLLMgramBot/conversation.py
TeLLMgramBot/initialize.py
TeLLMgramBot/message_handlers.py
TeLLMgramBot/openai_singleton.py
TeLLMgramBot/tokenGPT.py
TeLLMgramBot/utils.py
TeLLMgramBot/web_utils.py
tellmgrambot-2.0.0.dist-info/licenses/LICENSE
tellmgrambot-2.0.0.dist-info/METADATA
tellmgrambot-2.0.0.dist-info/WHEEL
tellmgrambot-2.0.0.dist-info/top_level.txt
tellmgrambot-2.0.0.dist-info/RECORD
