Metadata-Version: 2.4
Name: TeLLMgramBot
Version: 2.0.0
Summary: OpenAI GPT, driven by Telegram
Home-page: https://github.com/Digital-Heresy/TeLLMgramBot
Author: Digital Heresy
Author-email: ronin.atx@gmail.com
License: MIT
Requires-Python: >=3.10
License-File: LICENSE
Requires-Dist: openai>=1.10.0
Requires-Dist: PyYAML
Requires-Dist: httpx
Requires-Dist: beautifulsoup4
Requires-Dist: typing
Requires-Dist: validators
Requires-Dist: python-telegram-bot
Requires-Dist: tiktoken
Dynamic: author
Dynamic: author-email
Dynamic: description
Dynamic: description-content-type
Dynamic: home-page
Dynamic: license
Dynamic: license-file
Dynamic: requires-dist
Dynamic: requires-python
Dynamic: summary
